langchain_aidr-0.1.0.dist-info/METADATA
langchain_aidr-0.1.0.dist-info/WHEEL
langchain_aidr-0.1.0.dist-info/entry_points.txt
langchain_aidr-0.1.0.dist-info/licenses/LICENSE.txt
langchain_aidr/__init__.py
langchain_aidr/document_transformers/aidr_text_guard.py
langchain_aidr/py.typed
langchain_aidr/tools/ai_guard.py
langchain_aidr/tools/base.py
langchain_aidr-0.1.0.dist-info/RECORD
