Metadata-Version: 2.4
Name: langchain-aidr
Version: 0.1.0
Summary: LangChain integrations for CrowdStrike AIDR
Author-Email: CrowdStrike <support@crowdstrike.com>
License-Expression: MIT
Classifier: Typing :: Typed
Classifier: Intended Audience :: Developers
Classifier: Programming Language :: Python :: 3.12
Classifier: Programming Language :: Python :: 3.13
Classifier: Programming Language :: Python :: 3.14
Classifier: Operating System :: OS Independent
Classifier: Operating System :: POSIX
Classifier: Operating System :: MacOS
Classifier: Operating System :: POSIX :: Linux
Classifier: Operating System :: Microsoft :: Windows
Classifier: Topic :: Software Development :: Libraries :: Python Modules
Project-URL: Source Code, https://github.com/CrowdStrike/langchain-aidr
Project-URL: Release Notes, https://github.com/CrowdStrike/langchain-aidr/releases
Requires-Python: >=3.13
Requires-Dist: crowdstrike-aidr~=0.2.0
Requires-Dist: langchain-core~=1.1.3
Requires-Dist: pydantic~=2.12.5
Requires-Dist: typing-extensions~=4.15.0
